mrkdwn/__init__.py
mrkdwn/main.py
mrkdwn-0.1.2.data/scripts/installer.bat
mrkdwn-0.1.2.data/scripts/installer.sh
mrkdwn-0.1.2.dist-info/LICENSE
mrkdwn-0.1.2.dist-info/METADATA
mrkdwn-0.1.2.dist-info/WHEEL
mrkdwn-0.1.2.dist-info/entry_points.txt
mrkdwn-0.1.2.dist-info/top_level.txt
mrkdwn-0.1.2.dist-info/RECORD
