Metadata-Version: 2.1
Name: mrkdwn
Version: 0.1.2
Summary: A tool to generate markdown from directory contents
Home-page: https://github.com/schizoprada/mrkdwn
Author: Joel Yisrael Biton
Author-email: joel@sss.bot
Classifier: Programming Language :: Python :: 3
Classifier: License :: OSI Approved :: MIT License
Classifier: Operating System :: OS Independent
Requires-Python: >=3.0
License-File: LICENSE
